pgfutils.py
matplotlib_pgfutils-1.7.0.data/data/share/matplotlib-pgfutils/latexmkrc
matplotlib_pgfutils-1.7.0.data/data/share/matplotlib-pgfutils/pgfutils.cfg
matplotlib_pgfutils-1.7.0.data/data/share/matplotlib-pgfutils/examples/README.md
matplotlib_pgfutils-1.7.0.data/data/share/matplotlib-pgfutils/examples/threecol/Makefile
matplotlib_pgfutils-1.7.0.data/data/share/matplotlib-pgfutils/examples/threecol/double.py
matplotlib_pgfutils-1.7.0.data/data/share/matplotlib-pgfutils/examples/threecol/latexmkrc
matplotlib_pgfutils-1.7.0.data/data/share/matplotlib-pgfutils/examples/threecol/pgfutils.cfg
matplotlib_pgfutils-1.7.0.data/data/share/matplotlib-pgfutils/examples/threecol/single.py
matplotlib_pgfutils-1.7.0.data/data/share/matplotlib-pgfutils/examples/threecol/threecol.tex
matplotlib_pgfutils-1.7.0.data/data/share/matplotlib-pgfutils/examples/threecol/triple.py
matplotlib_pgfutils-1.7.0.data/data/share/matplotlib-pgfutils/examples/twocol/Makefile
matplotlib_pgfutils-1.7.0.data/data/share/matplotlib-pgfutils/examples/twocol/double.py
matplotlib_pgfutils-1.7.0.data/data/share/matplotlib-pgfutils/examples/twocol/latexmkrc
matplotlib_pgfutils-1.7.0.data/data/share/matplotlib-pgfutils/examples/twocol/pgfutils.cfg
matplotlib_pgfutils-1.7.0.data/data/share/matplotlib-pgfutils/examples/twocol/single.py
matplotlib_pgfutils-1.7.0.data/data/share/matplotlib-pgfutils/examples/twocol/twocol.tex
matplotlib_pgfutils-1.7.0.dist-info/LICENSE
matplotlib_pgfutils-1.7.0.dist-info/METADATA
matplotlib_pgfutils-1.7.0.dist-info/WHEEL
matplotlib_pgfutils-1.7.0.dist-info/top_level.txt
matplotlib_pgfutils-1.7.0.dist-info/RECORD
