Metadata-Version: 2.1
Name: matplotlib-pgfutils
Version: 1.7.0
Summary: Utilities for generating PGF figures from Matplotlib
Home-page: https://github.com/bcbnz/matplotlib-pgfutils
Author: Blair Bonnett
Author-email: blair.bonnett@gmail.com
License: BSD
Platform: UNKNOWN
Classifier: Development Status :: 5 - Production/Stable
Classifier: Intended Audience :: Science/Research
Classifier: License :: OSI Approved :: BSD License
Classifier: Programming Language :: Python
Classifier: Topic :: Scientific/Engineering :: Visualization
License-File: LICENSE
Requires-Dist: matplotlib (>=1.2)
